{
  "image_index": 144,
  "model_name": "google/medgemma-4b-it",
  "provider": "huggingface",
  "strategy": "basic",
  "system_prompt": "You are a medical imaging AI assistant.",
  "user_prompt": "Describe this chest X-ray image. Identify any abnormalities you observe and provide your assessment.",
  "raw_response": "Okay, I've analyzed the chest X-ray image you provided. Here's a description and assessment:\n\n**Description:**\n\nThe image appears to be a chest X-ray showing the lungs and heart. The lungs are well-expanded. The heart size appears within normal limits. The mediastinum (the space between the lungs containing the heart, great vessels, trachea, etc.) appears unremarkable. There are no obvious signs of significant consolidation, pleural effusion, or pneumothorax.\n\n**Abnormalities Observed:**\n\n*   **No Obvious Abnormalities:** Based on the image, there are no immediately apparent abnormalities such as masses, nodules, consolidations, effusions, or pneumothorax.\n\n**Assessment:**\n\nThe chest X-ray appears normal. However, it is important to note that a single image is not sufficient for a definitive diagnosis. Further evaluation, including clinical history, physical examination, and potentially additional imaging (such as a CT scan), would be necessary to rule out any subtle abnormalities that may not be visible on this single view.\n\n**Disclaimer:**\n\nAs an AI, I am not a substitute for a qualified radiologist or medical professional. This assessment is based solely on the image provided and should not be used for diagnosis or treatment. A radiologist's interpretation is crucial for accurate diagnosis and treatment planning.",
  "ground_truth": 0,
  "cnn_prediction": 1,
  "cnn_confidence": 0.5275219678878784,
  "generation_time_s": 117.51
}